pulsar/__init__.py
pulsar/api.py
pulsar/apps/__init__.py
pulsar/apps/data/__init__.py
pulsar/apps/data/channels.py
pulsar/apps/data/store.py
pulsar/apps/data/pulsards/__init__.py
pulsar/apps/data/pulsards/startds.py
pulsar/apps/data/redis/__init__.py
pulsar/apps/data/redis/client.py
pulsar/apps/data/redis/lock.py
pulsar/apps/data/redis/pubsub.py
pulsar/apps/data/redis/store.py
pulsar/apps/ds/__init__.py
pulsar/apps/ds/client.py
pulsar/apps/ds/parser.py
pulsar/apps/ds/server.py
pulsar/apps/ds/utils.py
pulsar/apps/greenio/__init__.py
pulsar/apps/greenio/http.py
pulsar/apps/greenio/lock.py
pulsar/apps/greenio/pool.py
pulsar/apps/greenio/utils.py
pulsar/apps/greenio/wsgi.py
pulsar/apps/http/__init__.py
pulsar/apps/http/auth.py
pulsar/apps/http/client.py
pulsar/apps/http/decompress.py
pulsar/apps/http/oauth.py
pulsar/apps/http/plugins.py
pulsar/apps/http/stream.py
pulsar/apps/http/wsgi.py
pulsar/apps/rpc/__init__.py
pulsar/apps/rpc/handlers.py
pulsar/apps/rpc/jsonrpc.py
pulsar/apps/rpc/mixins.py
pulsar/apps/socket/__init__.py
pulsar/apps/test/__init__.py
pulsar/apps/test/cov.py
pulsar/apps/test/loader.py
pulsar/apps/test/populate.py
pulsar/apps/test/result.py
pulsar/apps/test/runner.py
pulsar/apps/test/utils.py
pulsar/apps/test/wsgi.py
pulsar/apps/test/plugins/__init__.py
pulsar/apps/test/plugins/base.py
pulsar/apps/test/plugins/bench.py
pulsar/apps/test/plugins/profile.py
pulsar/apps/test/plugins/htmlfiles/profile/index.html
pulsar/apps/test/plugins/htmlfiles/profile/jquery.tablesorter.min.js
pulsar/apps/test/plugins/htmlfiles/profile/profile.js
pulsar/apps/test/plugins/htmlfiles/profile/style.css
pulsar/apps/ws/__init__.py
pulsar/apps/ws/extensions.py
pulsar/apps/ws/websocket.py
pulsar/apps/wsgi/__init__.py
pulsar/apps/wsgi/auth.py
pulsar/apps/wsgi/content.py
pulsar/apps/wsgi/formdata.py
pulsar/apps/wsgi/handlers.py
pulsar/apps/wsgi/headers.py
pulsar/apps/wsgi/html.py
pulsar/apps/wsgi/middleware.py
pulsar-2.0.2.dist-info/DESCRIPTION.rst
pulsar-2.0.2.dist-info/METADATA
pulsar-2.0.2.dist-info/RECORD
pulsar-2.0.2.dist-info/WHEEL
pulsar-2.0.2.dist-info/entry_points.txt
pulsar-2.0.2.dist-info/metadata.json
pulsar-2.0.2.dist-info/top_level.txt
